odoo/addons/stock_inventory_analytic/README.rst
odoo/addons/stock_inventory_analytic/__init__.py
odoo/addons/stock_inventory_analytic/__manifest__.py
odoo/addons/stock_inventory_analytic/i18n/stock_inventory_analytic.pot
odoo/addons/stock_inventory_analytic/models/__init__.py
odoo/addons/stock_inventory_analytic/models/stock_inventory_line.py
odoo/addons/stock_inventory_analytic/readme/CONTRIBUTORS.rst
odoo/addons/stock_inventory_analytic/readme/DESCRIPTION.rst
odoo/addons/stock_inventory_analytic/static/description/icon.png
odoo/addons/stock_inventory_analytic/static/description/index.html
odoo/addons/stock_inventory_analytic/tests/__init__.py
odoo/addons/stock_inventory_analytic/tests/test_stock_inventory_analytic.py
odoo/addons/stock_inventory_analytic/views/stock_inventory_line_view.xml
odoo/addons/stock_inventory_analytic/wizard/__init__.py
odoo/addons/stock_inventory_analytic/wizard/stock_change_product_qty.py
odoo/addons/stock_inventory_analytic/wizard/stock_product_change_qty.xml
odoo11_addon_stock_inventory_analytic-11.0.1.0.0.99.dev4.dist-info/METADATA
odoo11_addon_stock_inventory_analytic-11.0.1.0.0.99.dev4.dist-info/WHEEL
odoo11_addon_stock_inventory_analytic-11.0.1.0.0.99.dev4.dist-info/top_level.txt
odoo11_addon_stock_inventory_analytic-11.0.1.0.0.99.dev4.dist-info/RECORD
